pypkgs_isa/__init__.py
pypkgs_isa/pypkgs_isa.py
pypkgs_isa-0.1.0.dist-info/LICENSE
pypkgs_isa-0.1.0.dist-info/WHEEL
pypkgs_isa-0.1.0.dist-info/METADATA
pypkgs_isa-0.1.0.dist-info/RECORD
